memhole/__about__.py
memhole/__init__.py
memhole/memhole.py
memhole/memhole_lib.so
memhole-1.0.0.dist-info/METADATA
memhole-1.0.0.dist-info/WHEEL
memhole-1.0.0.dist-info/licenses/LICENSE.txt
memhole-1.0.0.dist-info/RECORD
