Metadata-Version: 2.1
Name: memhole
Version: 1.0.0
Summary: Python wrapper for the memhole kernel module (includes memhole installer)
Project-URL: Documentation, https://github.com/unknown/memhole#readme
Project-URL: Issues, https://github.com/unknown/memhole/issues
Project-URL: Source, https://github.com/unknown/memhole
Author-email: Jacob Rice <wayzata20@gmail.com>
License-File: LICENSE.txt
Classifier: Development Status :: 4 - Beta
Classifier: Programming Language :: Python
Classifier: Programming Language :: Python :: 3.7
Classifier: Programming Language :: Python :: 3.8
Classifier: Programming Language :: Python :: 3.9
Classifier: Programming Language :: Python :: 3.10
Classifier: Programming Language :: Python :: 3.11
Classifier: Programming Language :: Python :: Implementation :: CPython
Classifier: Programming Language :: Python :: Implementation :: PyPy
Requires-Python: >=3.7
